{"/etc/issue.net":"Debian GNU/Linux 13","antiFeatures":{},"apksigner":"/usr/bin/apksigner","archivePolicy0":[],"commandLine":["/usr/bin/fdroid update","-c"],"disabled":[],"endTimestamp":1756834936278,"failedBuilds":{},"fdroiddata":{"commitId":"e15df271889daeea4263cc03cdf0cb40f87e1326","isDirty":false,"modifiedFiles":[],"untrackedFiles":[]},"jarsigner":"/usr/lib/jvm/default-java/bin/jarsigner","keytool":"/usr/lib/jvm/default-java/bin/keytool","needsUpdate":["5aca750cf697941c92aedd2b4942669b1ff28ad0141444d437d58365897ea0ea","com.escorial.transferencias"],"noPackages":["5aca750cf697941c92aedd2b4942669b1ff28ad0141444d437d58365897ea0ea","com.escorial.transferencias"],"noUpdateCheck":["5aca750cf697941c92aedd2b4942669b1ff28ad0141444d437d58365897ea0ea","com.escorial.transferencias"],"stages":{"delete_disabled_builds":1756834932886,"index.make repo":1756834932892,"prepare_apps repo":1756834932891,"process_apks":1756834932887,"read_added_date_from_all_apks":1756834932891,"remove_apks":1756834932888,"scan_repo_files":1756834932887},"startTimestamp":1756834931000,"subcommand":"update"}